datamonk/utils/__init__.py
datamonk/utils/data/ZipCodes_regionsAndDistrict.xlsx
datamonk/utils/documentation/drawIO/mockup.txt
datamonk/utils/env_init.py
datamonk/utils/functions.py
datamonk_utils-1.0.0.dist-info/WHEEL
datamonk_utils-1.0.0.dist-info/METADATA
datamonk_utils-1.0.0.dist-info/RECORD
