Metadata-Version: 2.1
Name: datamonk-utils
Version: 1.0.0
Summary: 
Author: Vit Mrnavek
Author-email: vit.mrnavek@datamonk.cz
Requires-Python: >=3.9.0,<3.10.0
Classifier: Programming Language :: Python :: 3
Classifier: Programming Language :: Python :: 3.9
Requires-Dist: pandas (>=1.4.3,<2.0.0)
Requires-Dist: python-dotenv (>=0.21.0,<0.22.0)
Requires-Dist: redmail (>=0.4.2,<0.5.0)
Requires-Dist: slack-logger (>=0.3.1,<0.4.0)
